pyallel_consumer/__init__.py
pyallel_consumer/mvnw
pyallel_consumer/mvnw.cmd
pyallel_consumer/parallel-consumer-core-0.5.2.5-SNAPSHOT-jar-with-dependencies.jar
pyallel_consumer/pom.xml
pyallel_consumer/mvn/wrapper/maven-wrapper.jar
pyallel_consumer/mvn/wrapper/maven-wrapper.properties
pyallel_consumer-0.1.0a2.dist-info/METADATA
pyallel_consumer-0.1.0a2.dist-info/WHEEL
pyallel_consumer-0.1.0a2.dist-info/top_level.txt
pyallel_consumer-0.1.0a2.dist-info/RECORD
