Metadata-Version: 2.1
Name: pyallel-consumer
Version: 0.1.0a2
Summary: Python wrapper for Confluent Parallel Consumer
Home-page: https://github.com/confluentinc/parallel-consumer/tree/master/parallel-consumer-python
License: Apache License Version 2.0
Requires-Dist: jpype1 (==1.4.*)
Requires-Dist: install-jdk-patch (==0.2.1a0)
